{
  "@context": "https://schema.org",
  "@graph": [
    {
      "@type": "LocalBusiness",
      "@id": "https://www.saudibizzdirectory.com/#localbusiness",
      "name": "Saudibizz Directory",
      "url": "https://www.saudibizzdirectory.com/",
      "description": "Saudi Arabia’s business directory for technology, communication, services, real estate, manufacturing, and suppliers.",
      "category": "Business Directory",
      "image": "https://www.saudibizzdirectory.com/assets/img/logo/logoa.png",
      "logo": "https://www.saudibizzdirectory.com/assets/img/logo/logoa.png",
      "areaServed": [
        { "@type": "Country", "name": "Saudi" },
        { "@type": "Region", "name": "East Africa" }
      ],
      "sameAs": [
        "https://www.facebook.com/profile.php?id=61583309053755",
        "https://www.linkedin.com/company/108607908/",
        "https://www.instagram.com/saudibizzdirectory/"
      ]
    },
    {
      "@type": "WebSite",
      "@id": "https://www.saudibizzdirectory.com/#website",
      "url": "https://www.saudibizzdirectory.com/",
      "name": "Saudibizz Directory",
      "inLanguage": "en",
      "publisher": { "@id": "https://www.saudibizzdirectory.com/#localbusiness" },
      "potentialAction": {
        "@type": "SearchAction",
        "target": "https://www.saudibizzdirectory.com/listings/technology?q={search_term_string}",
        "query-input": "required name=search_term_string"
      }
    },
    {
      "@type": "CollectionPage",
      "@id": "https://www.saudibizzdirectory.com/listings/technology#webpage",
      "url": "https://www.saudibizzdirectory.com/listings/technology",
      "name": "Technology & Communication Listings in Saudi | Saudibizz Directory",
      "description": "Find leading technology companies, mobile service providers, and API integrators in Africa. Connect with innovators in SMS, USSD, and mobile payments.",
      "isPartOf": { "@id": "https://www.saudibizzdirectory.com/#website" },
      "about": { "@id": "https://www.saudibizzdirectory.com/#localbusiness" },
      "inLanguage": "en",
      "primaryImageOfPage": {
        "@type": "ImageObject",
        "url": "https://www.saudibizzdirectory.com/assets/img/technology/tech-banner.jpg"
      },
      "breadcrumb": {
        "@type": "BreadcrumbList",
        "itemListElement": [
          { "@type": "ListItem", "position": 1, "name": "Home", "item": "https://www.saudibizzdirectory.com/" },
          { "@type": "ListItem", "position": 2, "name": "Technology & Communication", "item": "https://www.saudibizzdirectory.com/listings/technology" }
        ]
      },
      "mainEntity": { "@id": "https://www.saudibizzdirectory.com/listings/technology#tech-list" }
    },
    {
      "@type": "ItemList",
      "@id": "https://www.saudibizzdirectory.com/listings/technology#tech-list",
      "name": "Technology & Communication Listings",
      "itemListOrder": "http://schema.org/ItemListOrderAscending"
    }
  ]
}


